auto_clean_data/__init__.py
auto_clean_data/auto_clean.py
auto_clean_data-0.1.dist-info/METADATA
auto_clean_data-0.1.dist-info/WHEEL
auto_clean_data-0.1.dist-info/entry_points.txt
auto_clean_data-0.1.dist-info/top_level.txt
auto_clean_data-0.1.dist-info/RECORD
